_nx_graphblas/__init__.py
graphblas_algorithms/__init__.py
graphblas_algorithms/conftest.py
graphblas_algorithms/interface.py
graphblas_algorithms/algorithms/__init__.py
graphblas_algorithms/algorithms/_bfs.py
graphblas_algorithms/algorithms/_helpers.py
graphblas_algorithms/algorithms/boundary.py
graphblas_algorithms/algorithms/cluster.py
graphblas_algorithms/algorithms/core.py
graphblas_algorithms/algorithms/cuts.py
graphblas_algorithms/algorithms/dag.py
graphblas_algorithms/algorithms/dominating.py
graphblas_algorithms/algorithms/efficiency_measures.py
graphblas_algorithms/algorithms/exceptions.py
graphblas_algorithms/algorithms/isolate.py
graphblas_algorithms/algorithms/lowest_common_ancestors.py
graphblas_algorithms/algorithms/reciprocity.py
graphblas_algorithms/algorithms/regular.py
graphblas_algorithms/algorithms/simple_paths.py
graphblas_algorithms/algorithms/smetric.py
graphblas_algorithms/algorithms/structuralholes.py
graphblas_algorithms/algorithms/tournament.py
graphblas_algorithms/algorithms/triads.py
graphblas_algorithms/algorithms/centrality/__init__.py
graphblas_algorithms/algorithms/centrality/degree_alg.py
graphblas_algorithms/algorithms/centrality/eigenvector.py
graphblas_algorithms/algorithms/centrality/katz.py
graphblas_algorithms/algorithms/community/__init__.py
graphblas_algorithms/algorithms/community/quality.py
graphblas_algorithms/algorithms/components/__init__.py
graphblas_algorithms/algorithms/components/connected.py
graphblas_algorithms/algorithms/components/weakly_connected.py
graphblas_algorithms/algorithms/isomorphism/__init__.py
graphblas_algorithms/algorithms/isomorphism/isomorph.py
graphblas_algorithms/algorithms/link_analysis/__init__.py
graphblas_algorithms/algorithms/link_analysis/hits_alg.py
graphblas_algorithms/algorithms/link_analysis/pagerank_alg.py
graphblas_algorithms/algorithms/operators/__init__.py
graphblas_algorithms/algorithms/operators/binary.py
graphblas_algorithms/algorithms/operators/unary.py
graphblas_algorithms-2023.10.0.dist-info/LICENSE
graphblas_algorithms-2023.10.0.dist-info/METADATA
graphblas_algorithms-2023.10.0.dist-info/WHEEL
graphblas_algorithms-2023.10.0.dist-info/entry_points.txt
graphblas_algorithms-2023.10.0.dist-info/top_level.txt
graphblas_algorithms-2023.10.0.dist-info/RECORD
