Metadata-Version: 2.1
Name: graphblas-algorithms
Version: 2023.10.0
Summary: Graph algorithms written in GraphBLAS and backend for NetworkX
Author: Jim Kitchen, Graphblas-algorithms contributors
Author-email: Erik Welch <erik.n.welch@gmail.com>
Maintainer-email: Erik Welch <erik.n.welch@gmail.com>, Jim Kitchen <jim22k@gmail.com>
License: Apache License
Project-URL: homepage, https://github.com/python-graphblas/graphblas-algorithms
Project-URL: repository, https://github.com/python-graphblas/graphblas-algorithms
Project-URL: changelog, https://github.com/python-graphblas/graphblas-algorithms/releases
Keywords: graphblas,graph,sparse,matrix,lagraph,suitesparse,Networks,Graph Theory,Mathematics,network,discrete mathematics,math
Classifier: Development Status :: 4 - Beta
Classifier: License :: OSI Approved :: Apache Software License
Classifier: Operating System :: MacOS :: MacOS X
Classifier: Operating System :: POSIX :: Linux
Classifier: Operating System :: Microsoft :: Windows
Classifier: Programming Language :: Python
Classifier: Programming Language :: Python :: 3
Classifier: Programming Language :: Python :: 3.9
Classifier: Programming Language :: Python :: 3.10
Classifier: Programming Language :: Python :: 3.11
Classifier: Programming Language :: Python :: 3.12
Classifier: Programming Language :: Python :: 3 :: Only
Classifier: Intended Audience :: Developers
Classifier: Intended Audience :: Other Audience
Classifier: Intended Audience :: Science/Research
Classifier: Topic :: Scientific/Engineering
Classifier: Topic :: Scientific/Engineering :: Bio-Informatics
Classifier: Topic :: Scientific/Engineering :: Information Analysis
Classifier: Topic :: Scientific/Engineering :: Mathematics
Classifier: Topic :: Scientific/Engineering :: Physics
Classifier: Topic :: Software Development :: Libraries :: Python Modules
Requires-Python: >=3.9
License-File: LICENSE
Requires-Dist: python-graphblas >=2023.1.0
Provides-Extra: all
Requires-Dist: graphblas-algorithms[test] ; extra == 'all'
Provides-Extra: test
Requires-Dist: pytest ; extra == 'test'
Requires-Dist: networkx >=3.0 ; extra == 'test'
Requires-Dist: scipy >=1.9 ; extra == 'test'
Requires-Dist: setuptools ; extra == 'test'
Requires-Dist: tomli ; extra == 'test'
